remove_bg_api/__init__.py
remove_bg_api-0.2.1.dist-info/LICENSE
remove_bg_api-0.2.1.dist-info/METADATA
remove_bg_api-0.2.1.dist-info/WHEEL
remove_bg_api-0.2.1.dist-info/top_level.txt
remove_bg_api-0.2.1.dist-info/RECORD
