Metadata-Version: 2.1
Name: remove-bg-api
Version: 0.2.1
Summary: Remove.bg Python API Wrapper
Home-page: https://github.com/OPHoperHPO/remove_bg_api
Author: Anodev (OPHoperHPO)
Author-email: netbook21@mail.ru
License: MIT
Keywords: remove_bg_api,removebg,api,wrapper
Platform: UNKNOWN
Classifier: Development Status :: 5 - Production/Stable
Classifier: Intended Audience :: Developers
Classifier: License :: OSI Approved :: MIT License
Classifier: Programming Language :: Python :: 3
Classifier: Programming Language :: Python :: 3.4
Classifier: Programming Language :: Python :: 3.5
Classifier: Programming Language :: Python :: 3.6
